randomstuff/__init__.py
randomstuff/_helper.py
randomstuff/ai_response.py
randomstuff/client.py
randomstuff/constants.py
randomstuff/covid.py
randomstuff/errors.py
randomstuff/joke.py
randomstuff/utils.py
randomstuff/waifu.py
randomstuff/weather.py
randomstuff.py-2.0.0.dist-info/LICENSE
randomstuff.py-2.0.0.dist-info/METADATA
randomstuff.py-2.0.0.dist-info/WHEEL
randomstuff.py-2.0.0.dist-info/top_level.txt
randomstuff.py-2.0.0.dist-info/RECORD
