Metadata-Version: 2.1
Name: randomstuff.py
Version: 2.0.0
Summary: An easy to use & feature-rich python API wrapper for Random Stuff API.
Home-page: https://github.com/nerdguyahmad/randomstuff.py
Author: nerdguyahmad
Author-email: nerdguyahmad.contact@gmail.com
License: MIT
Project-URL: Documentation, https://nerdguyahmad.gitbook.io/randomstuff
Project-URL: Source, https://github.com/nerdguyahmad/randomstuff.py
Project-URL: Tracker, https://github.com/nerdguyahmad/randomstuff.py/issues
Keywords: api-wrapper randomstuff api wrapper
Platform: UNKNOWN
Classifier: Development Status :: 3 - Alpha
Classifier: Intended Audience :: Developers
Classifier: Topic :: Software Development :: Build Tools
Classifier: License :: OSI Approved :: MIT License
Classifier: Programming Language :: Python :: 3
Classifier: Programming Language :: Python :: 3.6
Classifier: Programming Language :: Python :: 3.7
Classifier: Programming Language :: Python :: 3.8
Classifier: Programming Language :: Python :: 3.9
Requires-Python: >=3.6
Requires-Dist: aiohttp
Requires-Dist: requests
Requires-Dist: colorama
